{
    "type": "minecraft:crafting_shaped",
    "pattern": [
        "OSO",
        "SDS",
        "OTO"
    ],
    "key": {
        "O": {
            "item": "botania:orange_petal"
        },
        "S": {
            "item": "manastorage:16m_mana_storage_block"
        },
        "D": {
            "item": "botania:mana_diamond"
        },
        "T": {
            "item": "botania:terrasteel_ingot"
        }
    },
    "result": {
        "item": "manastorage:64m_mana_storage_block",
        "count": 1
    }
}